time_series_expectations/__init__.py
time_series_expectations/generator.py
time_series_expectations/expectations/__init__.py
time_series_expectations/expectations/column_aggregate_time_series_expectation.py
time_series_expectations/expectations/expect_batch_row_count_to_match_prophet_date_model.py
time_series_expectations/expectations/expect_column_max_to_match_prophet_date_model.py
time_series_expectations/expectations/expect_column_pair_values_to_match_prophet_date_model.py
time_series_expectations/expectations/prophet_model_deserializer.py
time_series_expectations/generator/__init__.py
time_series_expectations/generator/daily_time_series_generator.py
time_series_expectations/generator/hourly_time_series_generator.py
time_series_expectations/generator/monthly_time_series_generator.py
time_series_expectations/generator/time_series_generator.py
time_series_expectations/generator/weekly_time_series_generator.py
time_series_expectations/metrics/__init__.py
time_series_expectations/profilers/__init__.py
great_expectations_time_series_expectations-0.1.0.dist-info/LICENSE
great_expectations_time_series_expectations-0.1.0.dist-info/METADATA
great_expectations_time_series_expectations-0.1.0.dist-info/WHEEL
great_expectations_time_series_expectations-0.1.0.dist-info/top_level.txt
great_expectations_time_series_expectations-0.1.0.dist-info/RECORD
