Metadata-Version: 2.1
Name: great-expectations-time-series-expectations
Version: 0.1.0
Summary: Expectations for detecting trends, seasonality, outliers, etc. in time series data.
Author: Great Expectations
Author-email: austin@greatexpectations.io
License-File: LICENSE
Requires-Dist: great-expectations
Requires-Dist: numpy
Requires-Dist: pandas
Requires-Dist: prophet
Requires-Dist: setuptools
